README.md
setup.py
virtualchain/__init__.py
virtualchain/version.py
virtualchain/virtualchain.py
virtualchain.egg-info/PKG-INFO
virtualchain.egg-info/SOURCES.txt
virtualchain.egg-info/dependency_links.txt
virtualchain.egg-info/not-zip-safe
virtualchain.egg-info/requires.txt
virtualchain.egg-info/top_level.txt
virtualchain/impl_ref/__init__.py
virtualchain/impl_ref/reference.py
virtualchain/lib/__init__.py
virtualchain/lib/config.py
virtualchain/lib/ecdsalib.py
virtualchain/lib/encoding.py
virtualchain/lib/hashing.py
virtualchain/lib/indexer.py
virtualchain/lib/merkle.py
virtualchain/lib/blockchain/__init__.py
virtualchain/lib/blockchain/address.py
virtualchain/lib/blockchain/keys.py
virtualchain/lib/blockchain/scripts.py
virtualchain/lib/blockchain/session.py
virtualchain/lib/blockchain/transactions.py
virtualchain/lib/blockchain/bitcoin_blockchain/__init__.py
virtualchain/lib/blockchain/bitcoin_blockchain/authproxy.py
virtualchain/lib/blockchain/bitcoin_blockchain/bech32.py
virtualchain/lib/blockchain/bitcoin_blockchain/bits.py
virtualchain/lib/blockchain/bitcoin_blockchain/blocks.py
virtualchain/lib/blockchain/bitcoin_blockchain/fees.py
virtualchain/lib/blockchain/bitcoin_blockchain/keys.py
virtualchain/lib/blockchain/bitcoin_blockchain/multisig.py
virtualchain/lib/blockchain/bitcoin_blockchain/opcodes.py
virtualchain/lib/blockchain/bitcoin_blockchain/spv.py