Metadata-Version: 1.1
Name: virtualchain
Version: 0.20.0
Summary: A library for constructing virtual blockchains within a cryptocurrency's blockchain
Home-page: https://github.com/blockstack/virtualchain
Author: Blockstack.org
Author-email: support@blockstack.org
License: GPLv3
Download-URL: https://github.com/blockstack/virtualchain/archive/master.zip
Keywords: blockchain bitcoin btc cryptocurrency data
Platform: UNKNOWN
Classifier: Intended Audience :: Developers
Classifier: License :: OSI Approved :: GNU General Public License v3 (GPLv3)
Classifier: Operating System :: OS Independent
Classifier: Programming Language :: Python
Classifier: Topic :: Internet
Classifier: Topic :: Security :: Cryptography
Classifier: Topic :: Software Development :: Libraries :: Python Modules
